quantizetk/__init__.py
quantizetk/pipeline/__init__.py
quantizetk/pipeline/create.py
quantizetk/pipeline/load.py
quantizetk/shared/__init__.py
quantizetk/shared/constants.py
quantizetk/shared/pipeline.py
quantizetk/shared/utils/__init__.py
quantizetk/shared/utils/log_util.py
quantizetk/shared/utils/math_util.py
quantizetk/shared/utils/path_util.py
quantizetk-0.0.1.dist-info/METADATA
quantizetk-0.0.1.dist-info/WHEEL
quantizetk-0.0.1.dist-info/RECORD
