Metadata-Version: 2.1
Name: quantizetk
Version: 0.0.1
Summary: quantizetk
License: MIT
Author: wayfaring-stranger
Author-email: zw6p226m@duck.com
Requires-Python: >=3.8,<4.0
Classifier: License :: OSI Approved :: MIT License
Classifier: Programming Language :: Python :: 3
Classifier: Programming Language :: Python :: 3.8
Classifier: Programming Language :: Python :: 3.9
Classifier: Programming Language :: Python :: 3.10
Classifier: Programming Language :: Python :: 3.11
Requires-Dist: onnx (>=1.14.1,<2.0.0)
Requires-Dist: onnxruntime (>=1.15.1,<2.0.0)
Requires-Dist: optimum (>=1.13.1,<2.0.0)
